README.rst
setup.py
tdx/__init__.py
tdx/cli.py
tdx/collections.py
tdx/data.py
tdx/decorators.py
tdx/exceptions.py
tdx/inspectcall.py
tdx/validation.py
tdx/version.py
tdx.egg-info/PKG-INFO
tdx.egg-info/SOURCES.txt
tdx.egg-info/dependency_links.txt
tdx.egg-info/not-zip-safe
tdx.egg-info/requires.txt
tdx.egg-info/top_level.txt